HW2/HW1_alu.v
//IC LAB HW1

module alu(
             clk_p_i,
             reset_n_i,
             data_a_i,
             data_b_i,
             inst_i,
             data_o
             );

  /*========================IO declaration============================ */	  
      input           clk_p_i;
      input           reset_n_i;
      input   [7:0]   data_a_i;
      input   [7:0]   data_b_i;
      input   [2:0]   inst_i;

      output  [15:0]  data_o;

  /* =======================REG & wire================================ */
	  
      //declare reg&wire you need
      //parameters and logic
      parameter S_ADD = 0;
      parameter S_SUB = 1;
      parameter S_MUL = 2;
      parameter S_DVD = 3;
      parameter S_NSB = 4;
      parameter S_XOR = 5;
      parameter S_ABS = 6;
      wire [15:0]  out1, out2, out3, out4, out5, out6, out7;
	    reg [2:0] state_w, state_r;
      reg [15:0] out_r, out_w, data_a, data_b;
      
      //wire assignment
      assign out1 = data_a + data_b;
      assign out2 = $signed(data_b) - $signed(data_a);
      assign out3 = data_a * data_b;
      assign out4 = data_a >>> 1;
      assign out5 = ~ out2;
      assign out6 = data_a ^ data_b;
      assign out7 = out2[15] ? ~out2+1 : out2;
      assign data_o = out_r;

  /* ====================Combinational Part================== */
  //next-state logic

		always@(*) begin
      case(state_r)
        S_ADD:   state_w = inst_i == 7 ? state_r : inst_i;
        S_SUB:   state_w = inst_i == 7 ? state_r : inst_i;
        S_MUL:   state_w = inst_i == 0 || inst_i == 1 || inst_i == 3 || inst_i == 5 ? inst_i : state_r;  
        S_DVD:   state_w = inst_i == 0 || inst_i == 1 || inst_i == 6 ? inst_i : state_r;  
        S_NSB:   state_w = inst_i == 1 || inst_i == 5 ? inst_i : state_r;  
        S_XOR:   state_w = inst_i == 0 || inst_i == 1 || inst_i == 2 ? inst_i : state_r;  
        S_ABS:   state_w = inst_i == 1 || inst_i == 5 ? inst_i : state_r;  
        default: state_w = state_r;
      endcase
    end	  
			  
			  
  // output logic
    always@(*) begin
      case(state_r)
        S_ADD: out_w = out1;
        S_SUB: out_w = out2;
        S_MUL: out_w = out3;
        S_DVD: out_w = out4;
        S_NSB: out_w = out5;
        S_XOR: out_w = out6;
        S_ABS: out_w = out7;
        default: out_w = out_r;
      endcase
    end	  

  /* ====================Sequential Part=================== */
    always@(posedge clk_p_i or negedge reset_n_i)
    begin
        if (reset_n_i == 1'b0) begin
			     //todo
           out_r   <= 16'b0;
           state_r <= 3'b0; 
           data_a  <= 8'b0;
           data_b  <= 8'b0;
        end
        else begin
              //todo 
            out_r   <= out_w;
            state_r <= state_w;
            data_a  <= {8'b0,data_a_i};
            data_b  <= {8'b0,data_b_i};   
        end
    end
  /* ====================================================== */

endmodule

HW1/HW1_alu_tb.v
`timescale 1ns/10ps
`define CYCLE    10           	         // Modify your clock period here
//`define SDFFILE  "./alu.sdf"	         // Modify your sdf file name
`define IMAGE1     "./data1.dat"         // Modify your test image file
`define IMAGE2     "./data2.dat"         // Modify your test image file
`define CMD        "./cmd.dat"           // Modify your test cmd file
`define EXPECT     "./out_golden.dat"    // Modify your output golden file

module ALU_test;

parameter DATA_LENGTH   = 80;
parameter OUT_LENGTH    = 82;

reg           clk;
reg           reset;
reg   [7:0]   datain1,datain2;
reg   [2:0]   cmd;
wire  [15:0]  dataout;

reg   [2:0]   cmd_mem   [0:DATA_LENGTH-1];
reg   [15:0]  out_mem   [0:OUT_LENGTH-1];
reg   [7:0]   image1_mem  [0:DATA_LENGTH-1];
reg   [7:0]   image2_mem  [0:DATA_LENGTH-1];
reg   [15:0]  out_temp;

reg           stop;
integer       i, out_f, err, pattern_num;
reg           over;

   alu alu_0( .clk_p_i(clk), .reset_n_i(reset), .data_a_i(datain1), .data_b_i(datain2), .inst_i(cmd), .data_o(dataout) );          
   
//initial $sdf_annotate(`SDFFILE, top);
initial	$readmemh (`IMAGE1,  image1_mem);
initial	$readmemh (`IMAGE2,  image2_mem);
initial	$readmemh (`CMD,    cmd_mem);
initial	$readmemh (`EXPECT, out_mem);

initial begin
   clk         = 1'b1;
   reset       = 1'b1;
   stop        = 1'b0;  
   over        = 1'b0;
   pattern_num = 0;
   err         = 0;
   i           = 0;   
    #2.5 reset=1'b0;                            // system reset
    #2.5 reset=1'b1;

end

always begin #(`CYCLE/2) clk = ~clk; end

initial begin
	$dumpfile("alu.vcd");
	$dumpvars;

   out_f = $fopen("out.dat");
   if (out_f == 0) begin
        $display("Output file open error !");
        $finish;
   end
end


always @(negedge clk)begin
    if (i < OUT_LENGTH) begin
		 if(i < DATA_LENGTH)begin
          cmd      = cmd_mem[i];
          datain1  = image1_mem[i];
	       datain2  = image2_mem[i];
	    end
		 out_temp = out_mem[i];
	    i = i+1;      
    end
    else                                       
       stop = 1 ;      
end

always @(posedge clk)begin
    
    if(dataout !== out_temp && out_temp!==16'h0000) begin
        $display("ERROR at %d:output %h !=expect %h ",pattern_num-2, dataout, out_temp);
	    $fdisplay(out_f,"ERROR at %d:output %h !=expect %h ",pattern_num-2, dataout, out_temp);
        err = err + 1 ;
    end
    pattern_num = pattern_num + 1; 
    if(pattern_num === OUT_LENGTH)  over = 1'b1;
end

initial begin
      @(posedge stop)      
      if(over) begin
         $display("---------------------------------------------\n");
         if (err == 0)  begin
            $display("All data have been generated successfully!\n");
			$display("You will get 80 score in this RTL!\n");
            $display("-------------------PASS-------------------\n");
         end
         else begin
            $display("There are %d errors!\n", err);
			$display("You will get %d score in this RTL!\n", 80-err);
		 end
            $display("---------------------------------------------\n");
      end
      else begin
        $display("---------------------------------------------\n");
        $display("Error!!! There is no any data output ...!\n");
        $display("-------------------FAIL-------------------\n");
        $display("---------------------------------------------\n");
      end
      $finish;
end
   
endmodule

HW1/alu.vcd
$date
	Wed Feb 23 01:48:11 2022
$end
$version
	Icarus Verilog
$end
$timescale
	10ps
$end
$scope module ALU_test $end
$var wire 16 ! dataout [15:0] $end
$var reg 1 " clk $end
$var reg 3 # cmd [2:0] $end
$var reg 8 $ datain1 [7:0] $end
$var reg 8 % datain2 [7:0] $end
$var reg 16 & out_temp [15:0] $end
$var reg 1 ' over $end
$var reg 1 ( reset $end
$var reg 1 ) stop $end
$var integer 32 * err [31:0] $end
$var integer 32 + i [31:0] $end
$var integer 32 , out_f [31:0] $end
$var integer 32 - pattern_num [31:0] $end
$scope module alu_0 $end
$var wire 1 " clk_p_i $end
$var wire 8 . data_a_i [7:0] $end
$var wire 8 / data_b_i [7:0] $end
$var wire 16 0 data_o [15:0] $end
$var wire 3 1 inst_i [2:0] $end
$var wire 16 2 out5 [15:0] $end
$var wire 16 3 out6 [15:0] $end
$var wire 1 ( reset_n_i $end
$var wire 16 4 out7 [15:0] $end
$var wire 16 5 out4 [15:0] $end
$var wire 16 6 out3 [15:0] $end
$var wire 16 7 out2 [15:0] $end
$var wire 16 8 out1 [15:0] $end
$var reg 16 9 data_a [15:0] $end
$var reg 16 : data_b [15:0] $end
$var reg 16 ; out_r [15:0] $end
$var reg 16 < out_w [15:0] $end
$var reg 3 = state_r [2:0] $end
$var reg 3 > state_w [2:0] $end
$upscope $end
$upscope $end
$enddefinitions $end
#0
$dumpvars
bx >
bx =
bx <
bx ;
b0xxxxxxxx :
b0xxxxxxxx 9
bx 8
bx 7
bx 6
b0xxxxxxx 5
bx 4
b0xxxxxxxx 3
bx 2
bx 1
bx 0
bx /
bx .
b0 -
b10 ,
b0 +
b0 *
0)
1(
0'
bx &
bx %
bx $
bx #
1"
bx !
$end
#250
b0 4
b1111111111111111 2
b0 5
b0 3
b0 <
b0 8
b0 7
b0 6
b0 :
b0 9
b0 =
b0 !
b0 0
b0 ;
0(
#500
b0 >
b1 +
b0 &
b11111111 %
b11111111 /
b0 $
b0 .
b0 #
b0 1
1(
0"
#1000
b11111111 4
b1111111100000000 2
b11111111 <
b11111111 3
b11111111 8
b11111111 7
b11111111 :
b1 -
1"
#1500
b10 >
b10 +
b110110 %
b110110 /
b1 $
b1 .
b10 #
b10 1
0"
#2000
b110101 4
b1111111111001010 2
b110111 3
b110110 <
b110110 :
b110111 8
b110101 7
b110110 6
b1 9
b10 =
b11111111 !
b11111111 0
b11111111 ;
b10 -
1"
#2500
b11 >
b11 +
b11111111 &
b11100111 %
b11100111 /
b10 $
b10 .
b11 #
b11 1
0"
#3000
b11100101 4
b1111111100011010 2
b1 5
b11100101 3
b1 <
b11100111 :
b11101001 8
b11100101 7
b111001110 6
b10 9
b11 =
b110110 !
b110110 0
b110110 ;
b11 -
1"
#3500
b110 >
b100 +
b110110 &
b11110000 %
b11110000 /
b11 $
b11 .
b110 #
b110 1
0"
#4000
b11101101 4
b1111111100010010 2
b11110011 3
b11101101 <
b11110000 :
b11110011 8
b11101101 7
b1011010000 6
b11 9
b110 =
b1 !
b1 0
b1 ;
b100 -
1"
#4500
b101 >
b101 +
b1 &
b1010101 %
b1010101 /
b100 $
b100 .
b101 #
b101 1
0"
#5000
b1010001 4
b1111111110101110 2
b10 5
b1010001 3
b1010001 <
b1010101 :
b1011001 8
b1010001 7
b101010100 6
b100 9
b101 =
b11101101 !
b11101101 0
b11101101 ;
b101 -
1"
#5500
b1 >
b110 +
b11101101 &
b110010 %
b110010 /
b101 $
b101 .
b1 #
b1 1
0"
#6000
b101101 4
b1111111111010010 2
b110111 3
b101101 <
b110010 :
b110111 8
b101101 7
b11111010 6
b101 9
b1 =
b1010001 !
b1010001 0
b1010001 ;
b110 -
1"
#6500
b111 +
b1010001 &
b1110101 %
b1110101 /
b110 $
b110 .
b111 #
b111 1
0"
#7000
b1101111 4
b1111111110010000 2
b11 5
b1110011 3
b1101111 <
b1110101 :
b1111011 8
b1101111 7
b1010111110 6
b110 9
b101101 !
b101101 0
b101101 ;
b111 -
1"
#7500
b100 >
b1000 +
b101101 &
b1000010 %
b1000010 /
b111 $
b111 .
b100 #
b100 1
0"
#8000
b111011 4
b1111111111000100 2
b1000101 3
b1111111111000100 <
b1000010 :
b1001001 8
b111011 7
b111001110 6
b111 9
b100 =
b1101111 !
b1101111 0
b1101111 ;
b1000 -
1"
#8500
b1001 +
b1101111 &
b11 #
b11 1
0"
#9000
b1111111111000100 !
b1111111111000100 0
b1111111111000100 ;
b1001 -
1"
#9500
b1010 +
b1111111111000100 &
b0 #
b0 1
0"
#10000
b1010 -
1"
#10500
b1011 +
b10 #
b10 1
0"
#11000
b1011 -
1"
#11500
b1100 +
b100 #
b100 1
0"
#12000
b1100 -
1"
#12500
b1101 +
b110 #
b110 1
0"
#13000
b1101 -
1"
#13500
b101 >
b1110 +
b10101111 %
b10101111 /
b1101 $
b1101 .
b101 #
b101 1
0"
#14000
b10100010 4
b1111111101011101 2
b110 5
b10100010 3
b10100010 <
b10101111 :
b10111100 8
b10100010 7
b100011100011 6
b1101 9
b101 =
b1110 -
1"
#14500
b1111 +
b11 #
b11 1
0"
#15000
b10100010 !
b10100010 0
b10100010 ;
b1111 -
1"
#15500
b10000 +
b10100010 &
b100 #
b100 1
0"
#16000
b10000 -
1"
#16500
b10001 +
b101 #
b101 1
0"
#17000
b10001 -
1"
#17500
b10010 +
b110 #
b110 1
0"
#18000
b10010 -
1"
#18500
b10 >
b10011 +
b10010011 %
b10010011 /
b10010 $
b10010 .
b10 #
b10 1
0"
#19000
b10000001 4
b1111111101111110 2
b1001 5
b10000001 3
b101001010110 <
b10010011 :
b10100101 8
b10000001 7
b101001010110 6
b10010 9
b10 =
b10011 -
1"
#19500
b10100 +
0"
#20000
b101001010110 !
b101001010110 0
b101001010110 ;
b10100 -
1"
#20500
b10101 +
b101001010110 &
b100 #
b100 1
0"
#21000
b10101 -
1"
#21500
b10110 +
b110 #
b110 1
0"
#22000
b10110 -
1"
#22500
b11 >
b10111 +
b101 %
b101 /
b10110 $
b10110 .
b11 #
b11 1
0"
#23000
b10001 4
b10000 2
b1011 5
b10011 3
b1011 <
b101 :
b11011 8
b1111111111101111 7
b1101110 6
b10110 9
b11 =
b10111 -
1"
#23500
b11000 +
b11000101 %
b11000101 /
b10 #
b10 1
0"
#24000
b10101111 4
b1111111101010000 2
b11010011 3
b11011011 8
b10101111 7
b1000011101110 6
b11000101 :
b1011 !
b1011 0
b1011 ;
b11000 -
1"
#24500
b11001 +
b1011 &
b101000 %
b101000 /
b11 #
b11 1
0"
#25000
b10010 4
b1111111111101101 2
b111110 3
b111110 8
b10010 7
b1101110000 6
b101000 :
b11001 -
1"
#25500
b11010 +
b1000100 %
b1000100 /
b100 #
b100 1
0"
#26000
b101110 4
b1111111111010001 2
b1010010 3
b1011010 8
b101110 7
b10111011000 6
b1000100 :
b11010 -
1"
#26500
b11011 +
b1100010 %
b1100010 /
b101 #
b101 1
0"
#27000
b1001100 4
b1111111110110011 2
b1110100 3
b1111000 8
b1001100 7
b100001101100 6
b1100010 :
b11011 -
1"
#27500
b110 >
b11100 +
b1100110 %
b1100110 /
b11011 $
b11011 .
b110 #
b110 1
0"
#28000
b1001011 4
b1111111110110100 2
b1101 5
b1111101 3
b1001011 <
b1100110 :
b10000001 8
b1001011 7
b101011000010 6
b11011 9
b110 =
b11100 -
1"
#28500
b11101 +
b0 #
b0 1
0"
#29000
b1001011 !
b1001011 0
b1001011 ;
b11101 -
1"
#29500
b11110 +
b1001011 &
b10 #
b10 1
0"
#30000
b11110 -
1"
#30500
b11111 +
b11 #
b11 1
0"
#31000
b11111 -
1"
#31500
b100000 +
b100 #
b100 1
0"
#32000
b100000 -
1"
#32500
b100001 +
b110 #
b110 1
0"
#33000
b100001 -
1"
#33500
b100010 +
b111 #
b111 1
0"
#34000
b100010 -
1"
#34500
b1 >
b100011 +
b1001 %
b1001 /
b10 $
b10 .
b1 #
b1 1
0"
#35000
b111 4
b1111111111111000 2
b1 5
b1011 3
b111 <
b1001 :
b1011 8
b111 7
b10010 6
b10 9
b1 =
b100011 -
1"
#35500
b10 >
b100100 +
b11111111 %
b11111111 /
b11 $
b11 .
b10 #
b10 1
0"
#36000
b11111100 4
b1111111100000011 2
b11111100 3
b1011111101 <
b11111111 :
b100000010 8
b11111100 7
b1011111101 6
b11 9
b10 =
b111 !
b111 0
b111 ;
b100100 -
1"
#36500
b100101 +
b111 &
b1000000 %
b1000000 /
b100 $
b100 .
b111 #
b111 1
0"
#37000
b111100 4
b1111111111000011 2
b10 5
b1000100 3
b100000000 <
b1000000 :
b1000100 8
b111100 7
b100000000 6
b100 9
b1011111101 !
b1011111101 0
b1011111101 ;
b100101 -
1"
#37500
b100110 +
b1011111101 &
b11000 %
b11000 /
b101 $
b101 .
b10 #
b10 1
0"
#38000
b10011 4
b1111111111101100 2
b11101 3
b1111000 <
b11000 :
b11101 8
b10011 7
b1111000 6
b101 9
b100000000 !
b100000000 0
b100000000 ;
b100110 -
1"
#38500
b101 >
b100111 +
b100000000 &
b10000000 %
b10000000 /
b110 $
b110 .
b101 #
b101 1
0"
#39000
b1111010 4
b1111111110000101 2
b11 5
b10000110 3
b10000110 <
b10000000 :
b10000110 8
b1111010 7
b1100000000 6
b110 9
b101 =
b1111000 !
b1111000 0
b1111000 ;
b100111 -
1"
#39500
b10 >
b101000 +
b1111000 &
b110011 %
b110011 /
b111 $
b111 .
b10 #
b10 1
0"
#40000
b101100 4
b1111111111010011 2
b110100 3
b101100101 <
b110011 :
b111010 8
b101100 7
b101100101 6
b111 9
b10 =
b10000110 !
b10000110 0
b10000110 ;
b101000 -
1"
#40500
b1 >
b101001 +
b10000110 &
b11100110 %
b11100110 /
b1000 $
b1000 .
b1 #
b1 1
0"
#41000
b11011110 4
b1111111100100001 2
b100 5
b11101110 3
b11011110 <
b11100110 :
b11101110 8
b11011110 7
b11100110000 6
b1000 9
b1 =
b101100101 !
b101100101 0
b101100101 ;
b101001 -
1"
#41500
b101 >
b101010 +
b101100101 &
b11110000 %
b11110000 /
b1001 $
b1001 .
b101 #
b101 1
0"
#42000
b11100111 4
b1111111100011000 2
b11111001 3
b11111001 <
b11110000 :
b11111001 8
b11100111 7
b100001110000 6
b1001 9
b101 =
b11011110 !
b11011110 0
b11011110 ;
b101010 -
1"
#42500
b0 >
b101011 +
b11011110 &
b11101001 %
b11101001 /
b1010 $
b1010 .
b0 #
b0 1
0"
#43000
b11011111 4
b1111111100100000 2
b101 5
b11100011 3
b11110011 <
b11101001 :
b11110011 8
b11011111 7
b100100011010 6
b1010 9
b0 =
b11111001 !
b11111001 0
b11111001 ;
b101011 -
1"
#43500
b101 >
b101100 +
b11111001 &
b11101010 %
b11101010 /
b1011 $
b1011 .
b101 #
b101 1
0"
#44000
b11100001 3
b11100001 <
b11101010 :
b11110101 8
b11011111 7
b101000001110 6
b1011 9
b101 =
b11110011 !
b11110011 0
b11110011 ;
b101100 -
1"
#44500
b101101 +
b11110011 &
b10000111 %
b10000111 /
b1100 $
b1100 .
b111 #
b111 1
0"
#45000
b10001011 <
b1111011 4
b1111111110000100 2
b110 5
b10001011 3
b10000111 :
b10010011 8
b1111011 7
b11001010100 6
b1100 9
b11100001 !
b11100001 0
b11100001 ;
b101101 -
1"
#45500
b1 >
b101110 +
b11100001 &
b11011101 %
b11011101 /
b1101 $
b1101 .
b1 #
b1 1
0"
#46000
b11010000 4
b1111111100101111 2
b11010000 3
b11010000 <
b11011101 :
b11101010 8
b11010000 7
b101100111001 6
b1101 9
b1 =
b10001011 !
b10001011 0
b10001011 ;
b101110 -
1"
#46500
b100 >
b101111 +
b10001011 &
b11101101 %
b11101101 /
b1110 $
b1110 .
b100 #
b100 1
0"
#47000
b11011111 4
b1111111100100000 2
b111 5
b11100011 3
b1111111100100000 <
b11101101 :
b11111011 8
b11011111 7
b110011110110 6
b1110 9
b100 =
b11010000 !
b11010000 0
b11010000 ;
b101111 -
1"
#47500
b110000 +
b11010000 &
b10010101 %
b10010101 /
b1111 $
b1111 .
b111 #
b111 1
0"
#48000
b1111111101111001 <
b10000110 4
b1111111101111001 2
b10011010 3
b10010101 :
b10100100 8
b10000110 7
b100010111011 6
b1111 9
b1111111100100000 !
b1111111100100000 0
b1111111100100000 ;
b110000 -
1"
#48500
b110001 +
b1111111100100000 &
b1111000 %
b1111000 /
b10000 $
b10000 .
b0 #
b0 1
0"
#49000
b1111111110010111 <
b1101000 4
b1111111110010111 2
b1000 5
b1101000 3
b1111000 :
b10001000 8
b1101000 7
b11110000000 6
b10000 9
b1111111101111001 !
b1111111101111001 0
b1111111101111001 ;
b110001 -
1"
#49500
b110010 +
b1111111101111001 &
b11010100 %
b11010100 /
b10001 $
b10001 .
b100 #
b100 1
0"
#50000
b1111111100111100 <
b11000011 4
b1111111100111100 2
b11000101 3
b11010100 :
b11100101 8
b11000011 7
b111000010100 6
b10001 9
b1111111110010111 !
b1111111110010111 0
b1111111110010111 ;
b110010 -
1"
#50500
b1 >
b110011 +
b1111111110010111 &
b11010011 %
b11010011 /
b10010 $
b10010 .
b1 #
b1 1
0"
#51000
b11000001 4
b1111111100111110 2
b1001 5
b11000001 3
b11000001 <
b11010011 :
b11100101 8
b11000001 7
b111011010110 6
b10010 9
b1 =
b1111111100111100 !
b1111111100111100 0
b1111111100111100 ;
b110011 -
1"
#51500
b11 >
b110100 +
b1111111100111100 &
b10111011 %
b10111011 /
b10011 $
b10011 .
b11 #
b11 1
0"
#52000
b10101000 4
b1111111101010111 2
b10101000 3
b1001 <
b10111011 :
b11001110 8
b10101000 7
b110111100001 6
b10011 9
b11 =
b11000001 !
b11000001 0
b11000001 ;
b110100 -
1"
#52500
b110101 +
b11000001 &
b11110100 %
b11110100 /
b10100 $
b10100 .
b111 #
b111 1
0"
#53000
b1010 <
b11100000 4
b1111111100011111 2
b1010 5
b11100000 3
b11110100 :
b100001000 8
b11100000 7
b1001100010000 6
b10100 9
b1001 !
b1001 0
b1001 ;
b110101 -
1"
#53500
b110110 +
b1001 &
b1110111 %
b1110111 /
b10101 $
b10101 .
b11 #
b11 1
0"
#54000
b1100010 4
b1111111110011101 2
b1100010 3
b1110111 :
b10001100 8
b1100010 7
b100111000011 6
b10101 9
b1010 !
b1010 0
b1010 ;
b110110 -
1"
#54500
b1 >
b110111 +
b1010 &
b1010010 %
b1010010 /
b10110 $
b10110 .
b1 #
b1 1
0"
#55000
b111100 4
b1111111111000011 2
b1011 5
b1000100 3
b111100 <
b1010010 :
b1101000 8
b111100 7
b11100001100 6
b10110 9
b1 =
b110111 -
1"
#55500
b0 >
b111000 +
b11000011 %
b11000011 /
b10111 $
b10111 .
b0 #
b0 1
0"
#56000
b10101100 4
b1111111101010011 2
b11010100 3
b11011010 <
b11000011 :
b11011010 8
b10101100 7
b1000110000101 6
b10111 9
b0 =
b111100 !
b111100 0
b111100 ;
b111000 -
1"
#56500
b11 >
b111001 +
b111100 &
b11000100 %
b11000100 /
b11000 $
b11000 .
b11 #
b11 1
0"
#57000
b1100 5
b11011100 3
b1100 <
b11000100 :
b11011100 8
b10101100 7
b1001001100000 6
b11000 9
b11 =
b11011010 !
b11011010 0
b11011010 ;
b111001 -
1"
#57500
b0 >
b111010 +
b11011010 &
b10101010 %
b10101010 /
b11001 $
b11001 .
b0 #
b0 1
0"
#58000
b10010001 4
b1111111101101110 2
b10110011 3
b11000011 <
b10101010 :
b11000011 8
b10010001 7
b1000010011010 6
b11001 9
b0 =
b1100 !
b1100 0
b1100 ;
b111010 -
1"
#58500
b111011 +
b1100 &
b10110101 %
b10110101 /
b11010 $
b11010 .
b111 #
b111 1
0"
#59000
b10011011 4
b1111111101100100 2
b1101 5
b10101111 3
b11001111 <
b10110101 :
b11001111 8
b10011011 7
b1001001100010 6
b11010 9
b11000011 !
b11000011 0
b11000011 ;
b111011 -
1"
#59500
b111100 +
b11000011 &
b10010010 %
b10010010 /
b11011 $
b11011 .
0"
#60000
b1110111 4
b1111111110001000 2
b10001001 3
b10101101 <
b10010010 :
b10101101 8
b1110111 7
b111101100110 6
b11011 9
b11001111 !
b11001111 0
b11001111 ;
b111100 -
1"
#60500
b110 >
b111101 +
b11001111 &
b1000 %
b1000 /
b11100 $
b11100 .
b110 #
b110 1
0"
#61000
b10100 4
b10011 2
b1110 5
b10100 3
b10100 <
b1000 :
b100100 8
b1111111111101100 7
b11100000 6
b11100 9
b110 =
b10101101 !
b10101101 0
b10101101 ;
b111101 -
1"
#61500
b1 >
b111110 +
b10101101 &
b11101110 %
b11101110 /
b11101 $
b11101 .
b1 #
b1 1
0"
#62000
b11010001 4
b1111111100101110 2
b11110011 3
b11010001 <
b11101110 :
b100001011 8
b11010001 7
b1101011110110 6
b11101 9
b1 =
b10100 !
b10100 0
b10100 ;
b111110 -
1"
#62500
b111111 +
b10100 &
b10000000 %
b10000000 /
b11110 $
b11110 .
0"
#63000
b1100010 4
b1111111110011101 2
b1111 5
b10011110 3
b1100010 <
b10000000 :
b10011110 8
b1100010 7
b111100000000 6
b11110 9
b11010001 !
b11010001 0
b11010001 ;
b111111 -
1"
#63500
b0 >
b1000000 +
b11010001 &
b10101001 %
b10101001 /
b11111 $
b11111 .
b0 #
b0 1
0"
#64000
b10001010 4
b1111111101110101 2
b10110110 3
b11001000 <
b10101001 :
b11001000 8
b10001010 7
b1010001110111 6
b11111 9
b0 =
b1100010 !
b1100010 0
b1100010 ;
b1000000 -
1"
#64500
b1000001 +
b1100010 &
b11111111 %
b11111111 /
b0 $
b0 .
0"
#65000
b11111111 4
b1111111100000000 2
b0 5
b11111111 3
b11111111 <
b11111111 :
b11111111 8
b11111111 7
b0 6
b0 9
b11001000 !
b11001000 0
b11001000 ;
b1000001 -
1"
#65500
b1 >
b1000010 +
b11001000 &
b110110 %
b110110 /
b1 $
b1 .
b1 #
b1 1
0"
#66000
b110101 4
b1111111111001010 2
b110111 3
b110101 <
b110110 :
b110111 8
b110101 7
b110110 6
b1 9
b1 =
b11111111 !
b11111111 0
b11111111 ;
b1000010 -
1"
#66500
b110 >
b1000011 +
b11111111 &
b11100111 %
b11100111 /
b10 $
b10 .
b110 #
b110 1
0"
#67000
b11100101 <
b11100101 4
b1111111100011010 2
b1 5
b11100101 3
b11100111 :
b11101001 8
b11100101 7
b111001110 6
b10 9
b110 =
b110101 !
b110101 0
b110101 ;
b1000011 -
1"
#67500
b1 >
b1000100 +
b110101 &
b11110000 %
b11110000 /
b11 $
b11 .
b1 #
b1 1
0"
#68000
b11101101 4
b1111111100010010 2
b11110011 3
b11101101 <
b11110000 :
b11110011 8
b11101101 7
b1011010000 6
b11 9
b1 =
b11100101 !
b11100101 0
b11100101 ;
b1000100 -
1"
#68500
b0 >
b1000101 +
b11100101 &
b1010101 %
b1010101 /
b100 $
b100 .
b0 #
b0 1
0"
#69000
b1010001 4
b1111111110101110 2
b10 5
b1010001 3
b1011001 <
b1010101 :
b1011001 8
b1010001 7
b101010100 6
b100 9
b0 =
b11101101 !
b11101101 0
b11101101 ;
b1000101 -
1"
#69500
b110 >
b1000110 +
b11101101 &
b110010 %
b110010 /
b101 $
b101 .
b110 #
b110 1
0"
#70000
b101101 4
b1111111111010010 2
b110111 3
b101101 <
b110010 :
b110111 8
b101101 7
b11111010 6
b101 9
b110 =
b1011001 !
b1011001 0
b1011001 ;
b1000110 -
1"
#70500
b1 >
b1000111 +
b1011001 &
b1110101 %
b1110101 /
b110 $
b110 .
b1 #
b1 1
0"
#71000
b1101111 4
b1111111110010000 2
b11 5
b1110011 3
b1101111 <
b1110101 :
b1111011 8
b1101111 7
b1010111110 6
b110 9
b1 =
b101101 !
b101101 0
b101101 ;
b1000111 -
1"
#71500
b10 >
b1001000 +
b101101 &
b1000010 %
b1000010 /
b111 $
b111 .
b10 #
b10 1
0"
#72000
b111011 4
b1111111111000100 2
b1000101 3
b111001110 <
b1000010 :
b1001001 8
b111011 7
b111001110 6
b111 9
b10 =
b1101111 !
b1101111 0
b1101111 ;
b1001000 -
1"
#72500
b0 >
b1001001 +
b1101111 &
b11000 %
b11000 /
b1000 $
b1000 .
b0 #
b0 1
0"
#73000
b10000 4
b1111111111101111 2
b100 5
b10000 3
b100000 <
b11000 :
b100000 8
b10000 7
b11000000 6
b1000 9
b0 =
b111001110 !
b111001110 0
b111001110 ;
b1001001 -
1"
#73500
b100 >
b1001010 +
b111001110 &
b100000 %
b100000 /
b1001 $
b1001 .
b100 #
b100 1
0"
#74000
b10111 4
b1111111111101000 2
b101001 3
b1111111111101000 <
b100000 :
b101001 8
b10111 7
b100100000 6
b1001 9
b100 =
b100000 !
b100000 0
b100000 ;
b1001010 -
1"
#74500
b101 >
b1001011 +
b100000 &
b1010111 %
b1010111 /
b1010 $
b1010 .
b101 #
b101 1
0"
#75000
b1001101 4
b1111111110110010 2
b101 5
b1011101 3
b1011101 <
b1010111 :
b1100001 8
b1001101 7
b1101100110 6
b1010 9
b101 =
b1111111111101000 !
b1111111111101000 0
b1111111111101000 ;
b1001011 -
1"
#75500
b1001100 +
b1111111111101000 &
b110000 %
b110000 /
b1011 $
b1011 .
b111 #
b111 1
0"
#76000
b111011 <
b100101 4
b1111111111011010 2
b111011 3
b110000 :
b111011 8
b100101 7
b1000010000 6
b1011 9
b1011101 !
b1011101 0
b1011101 ;
b1001100 -
1"
#76500
b1001101 +
b1011101 &
b11101011 %
b11101011 /
b1100 $
b1100 .
b101 #
b101 1
0"
#77000
b11100111 <
b11011111 4
b1111111100100000 2
b110 5
b11100111 3
b11101011 :
b11110111 8
b11011111 7
b101100000100 6
b1100 9
b111011 !
b111011 0
b111011 ;
b1001101 -
1"
#77500
b1001110 +
b111011 &
b10101111 %
b10101111 /
b1101 $
b1101 .
b111 #
b111 1
0"
#78000
b10100010 <
b10100010 4
b1111111101011101 2
b10100010 3
b10101111 :
b10111100 8
b10100010 7
b100011100011 6
b1101 9
b11100111 !
b11100111 0
b11100111 ;
b1001110 -
1"
#78500
b1001111 +
b11100111 &
b11101100 %
b11101100 /
b1110 $
b1110 .
b100 #
b100 1
0"
#79000
b11100010 <
b11011110 4
b1111111100100001 2
b111 5
b11100010 3
b11101100 :
b11111010 8
b11011110 7
b110011101000 6
b1110 9
b10100010 !
b10100010 0
b10100010 ;
b1001111 -
1"
#79500
b0 >
b1010000 +
b10100010 &
b10001 %
b10001 /
b1111 $
b1111 .
b0 #
b0 1
0"
#80000
b10 4
b1111111111111101 2
b11110 3
b100000 <
b10001 :
b100000 8
b10 7
b11111111 6
b1111 9
b0 =
b11100010 !
b11100010 0
b11100010 ;
b1010000 -
1"
#80500
b1010001 +
b11100010 &
0"
#81000
b100000 !
b100000 0
b100000 ;
b1010001 -
1"
#81500
b1010010 +
b100000 &
0"
#82000
1'
b1010010 -
1"
#82500
1)
0"
